MANIFEST.in
setup.py
opps/__init__.py
opps/feedcrawler/__init__.py
opps/feedcrawler/admin.py
opps/feedcrawler/models.py
opps/feedcrawler/tasks.py
opps/feedcrawler/urls.py
opps/feedcrawler/views.py
opps/feedcrawler/actions/__init__.py
opps/feedcrawler/management/__init__.py
opps/feedcrawler/management/commands/__init__.py
opps/feedcrawler/management/commands/process_feeds.py
opps/feedcrawler/migrations/0001_initial.py
opps/feedcrawler/migrations/0002_auto__add_field_feed_interval.py
opps/feedcrawler/migrations/0003_auto.py
opps/feedcrawler/migrations/0004_auto__add_field_entry_entry_original_id.py
opps/feedcrawler/migrations/__init__.py
opps/feedcrawler/processors/__init__.py
opps/feedcrawler/processors/base.py
opps/feedcrawler/processors/category_brasil.py
opps/feedcrawler/processors/category_efe.py
opps/feedcrawler/processors/efe.py
opps/feedcrawler/processors/ftp.py
opps/feedcrawler/processors/ftptidy.py
opps/feedcrawler/processors/rss.py
opps/feedcrawler/processors/rss_news.py
opps_feedcrawler.egg-info/PKG-INFO
opps_feedcrawler.egg-info/SOURCES.txt
opps_feedcrawler.egg-info/dependency_links.txt
opps_feedcrawler.egg-info/namespace_packages.txt
opps_feedcrawler.egg-info/requires.txt
opps_feedcrawler.egg-info/top_level.txt