Metadata-Version: 1.1
Name: opps-feedcrawler
Version: 0.2.1
Summary: Feed reader App for Opps CMS
Home-page: http://oppsproject.org
Author: Bruno Cezar Rocha
Author-email: rochacbruno@gmail.com
License: MIT
Download-URL: https://github.com/opps/opps-feedcrawler/tarball/master
Keywords: rss parser opps cms django apps magazines websites
Platform: UNKNOWN
Classifier: Development Status :: 5 - Production/Stable
Classifier: Intended Audience :: Developers
Classifier: License :: OSI Approved :: MIT License
Classifier: Operating System :: OS Independent
Classifier: Framework :: Opps
Classifier: Programming Language :: Python
Classifier: Programming Language :: Python :: 2.7
Classifier: Operating System :: OS Independent
Classifier: Topic :: Internet :: WWW/HTTP :: Dynamic Content
Classifier: Topic :: Software Development :: Libraries :: Python Modules
